paperview/__init__.py
paperview/retrieval/__init__.py
paperview/retrieval/biorxiv_api.py
paperview/retrieval/biorxiv_s3.py
paperview/retrieval/pdf_extraction.py
paperview-0.1.0.dist-info/WHEEL
paperview-0.1.0.dist-info/METADATA
paperview-0.1.0.dist-info/RECORD
