Metadata-Version: 2.1
Name: paperview
Version: 0.1.0
Summary: 
Author: anaka
Author-email: alex.naka@gmail.com
Requires-Python: >=3.8,<4.0
Classifier: Programming Language :: Python :: 3
Classifier: Programming Language :: Python :: 3.10
Classifier: Programming Language :: Python :: 3.8
Classifier: Programming Language :: Python :: 3.9
Requires-Dist: Pillow (>=9.3.0,<10.0.0)
Requires-Dist: PyMuPDF (>=1.21.1,<2.0.0)
Requires-Dist: PyPDF2 (>=2.12.1,<3.0.0)
Requires-Dist: attrs (>=22.1.0,<23.0.0)
Requires-Dist: boto3 (>=1.26.32,<2.0.0)
Requires-Dist: bs4 (>=0.0.1,<0.0.2)
Requires-Dist: ipykernel (>=6.19.4,<7.0.0)
Requires-Dist: jupyter (>=1.0.0,<2.0.0)
Requires-Dist: notebook (>=6.5.2,<7.0.0)
Requires-Dist: pdfminer.six (>=20221105,<20221106)
Requires-Dist: pikepdf (>=6.2.6,<7.0.0)
Requires-Dist: pre-commit (>=2.20.0,<3.0.0)
Requires-Dist: pytest (>=7.2.0,<8.0.0)
Requires-Dist: requests (>=2.28.1,<3.0.0)
